pycketcasts/__init__.py
pycketcasts/_info.py
pycketcasts/pocketcasts.py
pycketcasts-1.0.1.dist-info/LICENSE
pycketcasts-1.0.1.dist-info/METADATA
pycketcasts-1.0.1.dist-info/WHEEL
pycketcasts-1.0.1.dist-info/top_level.txt
pycketcasts-1.0.1.dist-info/RECORD
